chordelia/__init__.py
chordelia/audio_playback.py
chordelia/chords.py
chordelia/intervals.py
chordelia/midi_playback.py
chordelia/midifile.py
chordelia/notes.py
chordelia/rhythm.py
chordelia/scales.py
chordelia-0.2.0.dist-info/METADATA
chordelia-0.2.0.dist-info/WHEEL
chordelia-0.2.0.dist-info/top_level.txt
chordelia-0.2.0.dist-info/RECORD
