Metadata-Version: 2.4
Name: chordelia
Version: 0.2.0
Summary: A comprehensive music theory library built around algorithmic approaches
Requires-Python: >=3.13
